[
  {
    "_id": "576b0ceaea06ef0a5f722986",
    "device": "dexcom",
    "date": 1466633241000,
    "dateString": "Wed Jun 22 18:07:21 EDT 2016",
    "sgv": 101,
    "direction": "Flat",
    "type": "sgv",
    "filtered": 140256,
    "unfiltered": 138208,
    "rssi": 191,
    "noise": 1,
    "glucose": 101
  },
  {
    "_id": "576b0bbeea06ef0a5f722982",
    "device": "dexcom",
    "date": 1466632941000,
    "dateString": "Wed Jun 22 18:02:21 EDT 2016",
    "sgv": 103,
    "direction": "Flat",
    "type": "sgv",
    "filtered": 142176,
    "unfiltered": 139328,
    "rssi": 189,
    "noise": 1,
    "glucose": 103
  },
  {
    "_id": "576b0a92ea06ef0a5f72297e",
    "device": "dexcom",
    "date": 1466632641000,
    "dateString": "Wed Jun 22 17:57:21 EDT 2016",
    "sgv": 104,
    "direction": "Flat",
    "type": "sgv",
    "filtered": 144352,
    "unfiltered": 140992,
    "rssi": 183,
    "noise": 1,
    "glucose": 104
  },
  {
    "_id": "576b0966ea06ef0a5f722977",
    "device": "dexcom",
    "date": 1466632341000,
    "dateString": "Wed Jun 22 17:52:21 EDT 2016",
    "sgv": 107,
    "direction": "Flat",
    "type": "sgv",
    "filtered": 146496,
    "unfiltered": 143168,
    "rssi": 189,
    "noise": 1,
    "glucose": 107
  },
  {
    "_id": "576b083aea06ef0a5f722970",
    "device": "dexcom",
    "date": 1466632041000,
    "dateString": "Wed Jun 22 17:47:21 EDT 2016",
    "sgv": 109,
    "direction": "Flat",
    "type": "sgv",
    "filtered": 148384,
    "unfiltered": 145504,
    "rssi": 188,
    "noise": 1,
    "glucose": 109
  },
  {
    "_id": "576b070eea06ef0a5f72296b",
    "device": "dexcom",
    "date": 1466631741000,
    "dateString": "Wed Jun 22 17:42:21 EDT 2016",
    "sgv": 110,
    "direction": "Flat",
    "type": "sgv",
    "filtered": 149600,
    "unfiltered": 146912,
    "rssi": 179,
    "noise": 1,
    "glucose": 110
  },
  {
    "_id": "576b05e2ea06ef0a5f722966",
    "device": "dexcom",
    "date": 1466631441000,
    "dateString": "Wed Jun 22 17:37:21 EDT 2016",
    "sgv": 113,
    "direction": "Flat",
    "type": "sgv",
    "filtered": 150048,
    "unfiltered": 149120,
    "rssi": 172,
    "noise": 1,
    "glucose": 113
  },
  {
    "_id": "576b04b6ea06ef0a5f722963",
    "device": "dexcom",
    "date": 1466631141000,
    "dateString": "Wed Jun 22 17:32:21 EDT 2016",
    "sgv": 114,
    "direction": "Flat",
    "type": "sgv",
    "filtered": 149792,
    "unfiltered": 150112,
    "rssi": 186,
    "noise": 1,
    "glucose": 114
  },
  {
    "_id": "576b038aea06ef0a5f72295d",
    "device": "dexcom",
    "date": 1466630841000,
    "dateString": "Wed Jun 22 17:27:21 EDT 2016",
    "sgv": 114,
    "direction": "Flat",
    "type": "sgv",
    "filtered": 149088,
    "unfiltered": 150176,
    "rssi": 181,
    "noise": 1,
    "glucose": 114
  },
  {
    "_id": "576b025eea06ef0a5f722958",
    "device": "dexcom",
    "date": 1466630541000,
    "dateString": "Wed Jun 22 17:22:21 EDT 2016",
    "sgv": 113,
    "direction": "Flat",
    "type": "sgv",
    "filtered": 148192,
    "unfiltered": 149440,
    "rssi": 191,
    "noise": 1,
    "glucose": 113
  }
]
