[
  {
    "_id": "57619598a252ef437d5a9abb",
    "device": "dexcom",
    "date": 1466012882000,
    "dateString": "Wed Jun 15 13:48:02 EDT 2016",
    "sgv": 112,
    "direction": "Flat",
    "type": "sgv",
    "filtered": 116160,
    "unfiltered": 115600,
    "rssi": 190,
    "noise": 1,
    "glucose": 112
  },
  {
    "_id": "5761946ca252ef437d5a9ab5",
    "device": "dexcom",
    "date": 1466012582000,
    "dateString": "Wed Jun 15 13:43:02 EDT 2016",
    "sgv": 112,
    "direction": "Flat",
    "type": "sgv",
    "filtered": 118096,
    "unfiltered": 115072,
    "rssi": 194,
    "noise": 1,
    "glucose": 112
  },
  {
    "_id": "57619340a252ef437d5a9ab2",
    "device": "dexcom",
    "date": 1466012282000,
    "dateString": "Wed Jun 15 13:38:02 EDT 2016",
    "sgv": 114,
    "direction": "Flat",
    "type": "sgv",
    "filtered": 120336,
    "unfiltered": 116448,
    "rssi": 178,
    "noise": 1,
    "glucose": 114
  },
  {
    "_id": "57619214a252ef437d5a9aab",
    "device": "dexcom",
    "date": 1466011982000,
    "dateString": "Wed Jun 15 13:33:02 EDT 2016",
    "sgv": 118,
    "direction": "Flat",
    "type": "sgv",
    "filtered": 122256,
    "unfiltered": 119248,
    "rssi": 191,
    "noise": 1,
    "glucose": 118
  },
  {
    "_id": "576190e8a252ef437d5a9aa9",
    "device": "dexcom",
    "date": 1466011682000,
    "dateString": "Wed Jun 15 13:28:02 EDT 2016",
    "sgv": 120,
    "direction": "Flat",
    "type": "sgv",
    "filtered": 123840,
    "unfiltered": 120864,
    "rssi": 186,
    "noise": 1,
    "glucose": 120
  },
  {
    "_id": "57618fbfa252ef437d5a9aa5",
    "device": "dexcom",
    "date": 1466011382000,
    "dateString": "Wed Jun 15 13:23:02 EDT 2016",
    "sgv": 124,
    "direction": "Flat",
    "type": "sgv",
    "filtered": 125680,
    "unfiltered": 123440,
    "rssi": 186,
    "noise": 1,
    "glucose": 124
  },
  {
    "_id": "57618e90a252ef437d5a9aa3",
    "device": "dexcom",
    "date": 1466011082000,
    "dateString": "Wed Jun 15 13:18:02 EDT 2016",
    "sgv": 128,
    "direction": "Flat",
    "type": "sgv",
    "filtered": 128112,
    "unfiltered": 125968,
    "rssi": 191,
    "noise": 1,
    "glucose": 128
  },
  {
    "_id": "57618d64a252ef437d5a9a9f",
    "device": "dexcom",
    "date": 1466010782000,
    "dateString": "Wed Jun 15 13:13:02 EDT 2016",
    "sgv": 127,
    "direction": "Flat",
    "type": "sgv",
    "filtered": 130928,
    "unfiltered": 125552,
    "rssi": 442,
    "noise": 1,
    "glucose": 127
  },
  {
    "_id": "57618c3ba252ef437d5a9a9c",
    "device": "dexcom",
    "type": "cal",
    "date": 1466010483000,
    "dateString": "Wed Jun 15 13:08:03 EDT 2016",
    "slope": 694.5247524752476,
    "intercept": 33754.49504950493,
    "scale": 1
  },
  {
    "_id": "57618c3ba252ef437d5a9a9a",
    "device": "dexcom",
    "date": 1466010482000,
    "dateString": "Wed Jun 15 13:08:02 EDT 2016",
    "sgv": 132,
    "direction": "Flat",
    "type": "sgv",
    "filtered": 133408,
    "unfiltered": 129104,
    "rssi": 178,
    "noise": 1,
    "glucose": 132
  }
]
