[
  {
    "_id": "577e03caea06ef0a5f726f19",
    "device": "dexcom",
    "date": 1467876226000,
    "dateString": "Thu Jul 07 03:23:46 EDT 2016",
    "sgv": 132,
    "direction": "Flat",
    "type": "sgv",
    "filtered": 158784,
    "unfiltered": 157184,
    "rssi": 186,
    "noise": 1,
    "glucose": 132
  },
  {
    "_id": "577e029bea06ef0a5f726f15",
    "device": "dexcom",
    "date": 1467875926000,
    "dateString": "Thu Jul 07 03:18:46 EDT 2016",
    "sgv": 134,
    "direction": "Flat",
    "type": "sgv",
    "filtered": 158336,
    "unfiltered": 158752,
    "rssi": 179,
    "noise": 1,
    "glucose": 134
  },
  {
    "_id": "577e0170ea06ef0a5f726f10",
    "device": "dexcom",
    "date": 1467875626000,
    "dateString": "Thu Jul 07 03:13:46 EDT 2016",
    "sgv": 132,
    "direction": "Flat",
    "type": "sgv",
    "filtered": 155424,
    "unfiltered": 157184,
    "rssi": 176,
    "noise": 1,
    "glucose": 132
  },
  {
    "_id": "577e0043ea06ef0a5f726f09",
    "device": "dexcom",
    "date": 1467875326000,
    "dateString": "Thu Jul 07 03:08:46 EDT 2016",
    "sgv": 132,
    "direction": "FortyFiveUp",
    "type": "sgv",
    "filtered": 149824,
    "unfiltered": 156704,
    "rssi": 179,
    "noise": 1,
    "glucose": 132
  },
  {
    "_id": "577dff16ea06ef0a5f726f05",
    "device": "dexcom",
    "date": 1467875026000,
    "dateString": "Thu Jul 07 03:03:46 EDT 2016",
    "sgv": 129,
    "direction": "FortyFiveUp",
    "type": "sgv",
    "filtered": 143232,
    "unfiltered": 154528,
    "rssi": 181,
    "noise": 1,
    "glucose": 129
  },
  {
    "_id": "577dfde9ea06ef0a5f726f01",
    "device": "dexcom",
    "date": 1467874726000,
    "dateString": "Thu Jul 07 02:58:46 EDT 2016",
    "sgv": 124,
    "direction": "Flat",
    "type": "sgv",
    "filtered": 137792,
    "unfiltered": 149536,
    "rssi": 180,
    "noise": 1,
    "glucose": 124
  },
  {
    "_id": "577dfcbeea06ef0a5f726efd",
    "device": "dexcom",
    "date": 1467874427000,
    "dateString": "Thu Jul 07 02:53:47 EDT 2016",
    "sgv": 112,
    "direction": "Flat",
    "type": "sgv",
    "filtered": 135168,
    "unfiltered": 138880,
    "rssi": 183,
    "noise": 1,
    "glucose": 112
  },
  {
    "_id": "577dfb92ea06ef0a5f726ef9",
    "device": "dexcom",
    "date": 1467874126000,
    "dateString": "Thu Jul 07 02:48:46 EDT 2016",
    "sgv": 110,
    "direction": "Flat",
    "type": "sgv",
    "filtered": 135840,
    "unfiltered": 136992,
    "rssi": 181,
    "noise": 1,
    "glucose": 110
  },
  {
    "_id": "577dfa66ea06ef0a5f726ef6",
    "device": "dexcom",
    "date": 1467873826000,
    "dateString": "Thu Jul 07 02:43:46 EDT 2016",
    "sgv": 109,
    "direction": "Flat",
    "type": "sgv",
    "filtered": 138880,
    "unfiltered": 136032,
    "rssi": 182,
    "noise": 1,
    "glucose": 109
  },
  {
    "_id": "577df939ea06ef0a5f726ef2",
    "device": "dexcom",
    "date": 1467873526000,
    "dateString": "Thu Jul 07 02:38:46 EDT 2016",
    "sgv": 108,
    "direction": "Flat",
    "type": "sgv",
    "filtered": 142112,
    "unfiltered": 135328,
    "rssi": 180,
    "noise": 1,
    "glucose": 108
  }
]
