[
  {
    "_id": "57630c94a252ef437d5a9fd4",
    "device": "dexcom",
    "date": 1466108875000,
    "dateString": "Thu Jun 16 16:27:55 EDT 2016",
    "sgv": 134,
    "direction": "Flat",
    "type": "sgv",
    "filtered": 149248,
    "unfiltered": 147680,
    "rssi": 188,
    "noise": 1,
    "glucose": 134
  },
  {
    "_id": "57630b68a252ef437d5a9fd1",
    "device": "dexcom",
    "date": 1466108575000,
    "dateString": "Thu Jun 16 16:22:55 EDT 2016",
    "sgv": 135,
    "direction": "Flat",
    "type": "sgv",
    "filtered": 149952,
    "unfiltered": 148608,
    "rssi": 189,
    "noise": 1,
    "glucose": 135
  },
  {
    "_id": "57630a3fa252ef437d5a9fcf",
    "device": "dexcom",
    "date": 1466108275000,
    "dateString": "Thu Jun 16 16:17:55 EDT 2016",
    "sgv": 136,
    "direction": "Flat",
    "type": "sgv",
    "filtered": 150688,
    "unfiltered": 150112,
    "rssi": 188,
    "noise": 1,
    "glucose": 136
  },
  {
    "_id": "57630916a252ef437d5a9fcb",
    "device": "dexcom",
    "date": 1466107975000,
    "dateString": "Thu Jun 16 16:12:55 EDT 2016",
    "sgv": 137,
    "direction": "Flat",
    "type": "sgv",
    "filtered": 151392,
    "unfiltered": 150592,
    "rssi": 169,
    "noise": 1,
    "glucose": 137
  },
  {
    "_id": "576307e6a252ef437d5a9fc6",
    "device": "dexcom",
    "date": 1466107675000,
    "dateString": "Thu Jun 16 16:07:55 EDT 2016",
    "sgv": 136,
    "direction": "Flat",
    "type": "sgv",
    "filtered": 151904,
    "unfiltered": 150208,
    "rssi": 191,
    "noise": 1,
    "glucose": 136
  },
  {
    "_id": "576306b7a252ef437d5a9fc3",
    "device": "dexcom",
    "date": 1466107375000,
    "dateString": "Thu Jun 16 16:02:55 EDT 2016",
    "sgv": 138,
    "direction": "Flat",
    "type": "sgv",
    "filtered": 151968,
    "unfiltered": 151808,
    "rssi": 183,
    "noise": 1,
    "glucose": 138
  },
  {
    "_id": "57630590a252ef437d5a9fbf",
    "device": "dexcom",
    "date": 1466107075000,
    "dateString": "Thu Jun 16 15:57:55 EDT 2016",
    "sgv": 139,
    "direction": "Flat",
    "type": "sgv",
    "filtered": 151872,
    "unfiltered": 152224,
    "rssi": 186,
    "noise": 1,
    "glucose": 139
  },
  {
    "_id": "5763045fa252ef437d5a9fbb",
    "device": "dexcom",
    "date": 1466106775000,
    "dateString": "Thu Jun 16 15:52:55 EDT 2016",
    "sgv": 139,
    "direction": "Flat",
    "type": "sgv",
    "filtered": 152224,
    "unfiltered": 152576,
    "rssi": 182,
    "noise": 1,
    "glucose": 139
  },
  {
    "_id": "57630334a252ef437d5a9fb8",
    "device": "dexcom",
    "date": 1466106475000,
    "dateString": "Thu Jun 16 15:47:55 EDT 2016",
    "sgv": 138,
    "direction": "Flat",
    "type": "sgv",
    "filtered": 152960,
    "unfiltered": 152032,
    "rssi": 184,
    "noise": 1,
    "glucose": 138
  },
  {
    "_id": "57630209a252ef437d5a9fb3",
    "device": "dexcom",
    "date": 1466106175000,
    "dateString": "Thu Jun 16 15:42:55 EDT 2016",
    "sgv": 138,
    "direction": "Flat",
    "type": "sgv",
    "filtered": 154016,
    "unfiltered": 151552,
    "rssi": 185,
    "noise": 1,
    "glucose": 138
  }
]
