[
  {
    "_id": "57777f1bea06ef0a5f725b6c",
    "device": "dexcom",
    "date": 1467449055000,
    "dateString": "Sat Jul 02 04:44:15 EDT 2016",
    "sgv": 106,
    "direction": "Flat",
    "type": "sgv",
    "filtered": 117360,
    "unfiltered": 116096,
    "rssi": 209,
    "noise": 1,
    "glucose": 106
  },
  {
    "_id": "57777df1ea06ef0a5f725b6a",
    "device": "dexcom",
    "date": 1467448755000,
    "dateString": "Sat Jul 02 04:39:15 EDT 2016",
    "sgv": 107,
    "direction": "Flat",
    "type": "sgv",
    "filtered": 117920,
    "unfiltered": 116320,
    "rssi": 209,
    "noise": 1,
    "glucose": 107
  },
  {
    "_id": "57777cc3ea06ef0a5f725b64",
    "device": "dexcom",
    "date": 1467448455000,
    "dateString": "Sat Jul 02 04:34:15 EDT 2016",
    "sgv": 107,
    "direction": "Flat",
    "type": "sgv",
    "filtered": 117696,
    "unfiltered": 116992,
    "rssi": 209,
    "noise": 1,
    "glucose": 107
  },
  {
    "_id": "57777b95ea06ef0a5f725b62",
    "device": "dexcom",
    "date": 1467448155000,
    "dateString": "Sat Jul 02 04:29:15 EDT 2016",
    "sgv": 109,
    "direction": "Flat",
    "type": "sgv",
    "filtered": 117232,
    "unfiltered": 118400,
    "rssi": 209,
    "noise": 1,
    "glucose": 109
  },
  {
    "_id": "57777a68ea06ef0a5f725b60",
    "device": "dexcom",
    "date": 1467447855000,
    "dateString": "Sat Jul 02 04:24:15 EDT 2016",
    "sgv": 110,
    "direction": "Flat",
    "type": "sgv",
    "filtered": 117600,
    "unfiltered": 118896,
    "rssi": 209,
    "noise": 1,
    "glucose": 110
  },
  {
    "_id": "5777793dea06ef0a5f725b5b",
    "device": "dexcom",
    "date": 1467447555000,
    "dateString": "Sat Jul 02 04:19:15 EDT 2016",
    "sgv": 108,
    "direction": "Flat",
    "type": "sgv",
    "filtered": 119120,
    "unfiltered": 117392,
    "rssi": 207,
    "noise": 1,
    "glucose": 108
  },
  {
    "_id": "57777814ea06ef0a5f725b55",
    "device": "dexcom",
    "date": 1467447255000,
    "dateString": "Sat Jul 02 04:14:15 EDT 2016",
    "sgv": 108,
    "direction": "Flat",
    "type": "sgv",
    "filtered": 120912,
    "unfiltered": 117040,
    "rssi": 207,
    "noise": 1,
    "glucose": 108
  },
  {
    "_id": "577776e6ea06ef0a5f725b52",
    "device": "dexcom",
    "date": 1467446955000,
    "dateString": "Sat Jul 02 04:09:15 EDT 2016",
    "sgv": 111,
    "direction": "Flat",
    "type": "sgv",
    "filtered": 121632,
    "unfiltered": 119392,
    "rssi": 208,
    "noise": 1,
    "glucose": 111
  },
  {
    "_id": "577775b9ea06ef0a5f725b4e",
    "device": "dexcom",
    "date": 1467446655000,
    "dateString": "Sat Jul 02 04:04:15 EDT 2016",
    "sgv": 113,
    "direction": "Flat",
    "type": "sgv",
    "filtered": 120928,
    "unfiltered": 120960,
    "rssi": 208,
    "noise": 1,
    "glucose": 113
  },
  {
    "_id": "5777748dea06ef0a5f725b4c",
    "device": "dexcom",
    "date": 1467446355000,
    "dateString": "Sat Jul 02 03:59:15 EDT 2016",
    "sgv": 115,
    "direction": "Flat",
    "type": "sgv",
    "filtered": 119856,
    "unfiltered": 122432,
    "rssi": 208,
    "noise": 1,
    "glucose": 115
  }
]
