[
  {
    "_id": "575bed3da252ef437d5a8821",
    "device": "dexcom",
    "date": 1465642106000,
    "dateString": "Sat Jun 11 06:48:26 EDT 2016",
    "sgv": 101,
    "direction": "Flat",
    "type": "sgv",
    "filtered": 144992,
    "unfiltered": 142816,
    "rssi": 186,
    "noise": 1,
    "glucose": 101
  },
  {
    "_id": "575bec11a252ef437d5a881f",
    "device": "dexcom",
    "date": 1465641806000,
    "dateString": "Sat Jun 11 06:43:26 EDT 2016",
    "sgv": 102,
    "direction": "Flat",
    "type": "sgv",
    "filtered": 146656,
    "unfiltered": 144320,
    "rssi": 190,
    "noise": 1,
    "glucose": 102
  },
  {
    "_id": "575beae3a252ef437d5a881b",
    "device": "dexcom",
    "date": 1465641506000,
    "dateString": "Sat Jun 11 06:38:26 EDT 2016",
    "sgv": 103,
    "direction": "Flat",
    "type": "sgv",
    "filtered": 147840,
    "unfiltered": 145184,
    "rssi": 190,
    "noise": 1,
    "glucose": 103
  },
  {
    "_id": "575be9b9a252ef437d5a8819",
    "device": "dexcom",
    "date": 1465641206000,
    "dateString": "Sat Jun 11 06:33:26 EDT 2016",
    "sgv": 105,
    "direction": "Flat",
    "type": "sgv",
    "filtered": 147936,
    "unfiltered": 146880,
    "rssi": 190,
    "noise": 1,
    "glucose": 105
  },
  {
    "_id": "575be88ba252ef437d5a8816",
    "device": "dexcom",
    "date": 1465640906000,
    "dateString": "Sat Jun 11 06:28:26 EDT 2016",
    "sgv": 106,
    "direction": "Flat",
    "type": "sgv",
    "filtered": 146912,
    "unfiltered": 148256,
    "rssi": 191,
    "noise": 1,
    "glucose": 106
  },
  {
    "_id": "575be75da252ef437d5a8813",
    "device": "dexcom",
    "date": 1465640606000,
    "dateString": "Sat Jun 11 06:23:26 EDT 2016",
    "sgv": 106,
    "direction": "Flat",
    "type": "sgv",
    "filtered": 145184,
    "unfiltered": 148032,
    "rssi": 190,
    "noise": 1,
    "glucose": 106
  },
  {
    "_id": "575be631a252ef437d5a880f",
    "device": "dexcom",
    "date": 1465640306000,
    "dateString": "Sat Jun 11 06:18:26 EDT 2016",
    "sgv": 104,
    "direction": "Flat",
    "type": "sgv",
    "filtered": 143520,
    "unfiltered": 146112,
    "rssi": 192,
    "noise": 1,
    "glucose": 104
  },
  {
    "_id": "575be505a252ef437d5a880d",
    "device": "dexcom",
    "date": 1465640006000,
    "dateString": "Sat Jun 11 06:13:26 EDT 2016",
    "sgv": 104,
    "direction": "Flat",
    "type": "sgv",
    "filtered": 142304,
    "unfiltered": 145376,
    "rssi": 191,
    "noise": 1,
    "glucose": 104
  },
  {
    "_id": "575be3dba252ef437d5a880b",
    "device": "dexcom",
    "date": 1465639706000,
    "dateString": "Sat Jun 11 06:08:26 EDT 2016",
    "sgv": 101,
    "direction": "Flat",
    "type": "sgv",
    "filtered": 141376,
    "unfiltered": 142336,
    "rssi": 192,
    "noise": 1,
    "glucose": 101
  },
  {
    "_id": "575be2afa252ef437d5a8809",
    "device": "dexcom",
    "date": 1465639406000,
    "dateString": "Sat Jun 11 06:03:26 EDT 2016",
    "sgv": 100,
    "direction": "Flat",
    "type": "sgv",
    "filtered": 140512,
    "unfiltered": 141376,
    "rssi": 194,
    "noise": 1,
    "glucose": 100
  }
]
