[
  {
    "_id": "57870e20ea06ef0a5f728a72",
    "device": "dexcom",
    "date": 1468468687000,
    "dateString": "Wed Jul 13 23:58:07 EDT 2016",
    "sgv": 148,
    "direction": "Flat",
    "type": "sgv",
    "filtered": 206016,
    "unfiltered": 205856,
    "rssi": 186,
    "noise": 1,
    "glucose": 148
  },
  {
    "_id": "57870cf3ea06ef0a5f728a69",
    "device": "dexcom",
    "date": 1468468387000,
    "dateString": "Wed Jul 13 23:53:07 EDT 2016",
    "sgv": 147,
    "direction": "Flat",
    "type": "sgv",
    "filtered": 206912,
    "unfiltered": 205440,
    "rssi": 186,
    "noise": 1,
    "glucose": 147
  },
  {
    "_id": "57870bc6ea06ef0a5f728a65",
    "device": "dexcom",
    "date": 1468468087000,
    "dateString": "Wed Jul 13 23:48:07 EDT 2016",
    "sgv": 148,
    "direction": "Flat",
    "type": "sgv",
    "filtered": 207904,
    "unfiltered": 205760,
    "rssi": 186,
    "noise": 1,
    "glucose": 148
  },
  {
    "_id": "57870a9bea06ef0a5f728a57",
    "device": "dexcom",
    "date": 1468467787000,
    "dateString": "Wed Jul 13 23:43:07 EDT 2016",
    "sgv": 150,
    "direction": "Flat",
    "type": "sgv",
    "filtered": 208832,
    "unfiltered": 208128,
    "rssi": 186,
    "noise": 1,
    "glucose": 150
  },
  {
    "_id": "5787096fea06ef0a5f728a53",
    "device": "dexcom",
    "date": 1468467487000,
    "dateString": "Wed Jul 13 23:38:07 EDT 2016",
    "sgv": 150,
    "direction": "Flat",
    "type": "sgv",
    "filtered": 209664,
    "unfiltered": 208224,
    "rssi": 193,
    "noise": 1,
    "glucose": 150
  },
  {
    "_id": "57870842ea06ef0a5f728a50",
    "device": "dexcom",
    "date": 1468467187000,
    "dateString": "Wed Jul 13 23:33:07 EDT 2016",
    "sgv": 150,
    "direction": "Flat",
    "type": "sgv",
    "filtered": 210304,
    "unfiltered": 208832,
    "rssi": 192,
    "noise": 1,
    "glucose": 150
  },
  {
    "_id": "57870716ea06ef0a5f728a4d",
    "device": "dexcom",
    "date": 1468466887000,
    "dateString": "Wed Jul 13 23:28:07 EDT 2016",
    "sgv": 152,
    "direction": "Flat",
    "type": "sgv",
    "filtered": 210496,
    "unfiltered": 210432,
    "rssi": 191,
    "noise": 1,
    "glucose": 152
  },
  {
    "_id": "578705ebea06ef0a5f728a49",
    "device": "dexcom",
    "date": 1468466587000,
    "dateString": "Wed Jul 13 23:23:07 EDT 2016",
    "sgv": 152,
    "direction": "Flat",
    "type": "sgv",
    "filtered": 210080,
    "unfiltered": 210272,
    "rssi": 186,
    "noise": 1,
    "glucose": 152
  },
  {
    "_id": "578704bfea06ef0a5f728a3f",
    "device": "dexcom",
    "date": 1468466287000,
    "dateString": "Wed Jul 13 23:18:07 EDT 2016",
    "sgv": 152,
    "direction": "Flat",
    "type": "sgv",
    "filtered": 208704,
    "unfiltered": 210432,
    "rssi": 186,
    "noise": 1,
    "glucose": 152
  },
  {
    "_id": "57870395ea06ef0a5f728a3c",
    "device": "dexcom",
    "date": 1468465987000,
    "dateString": "Wed Jul 13 23:13:07 EDT 2016",
    "sgv": 151,
    "direction": "Flat",
    "type": "sgv",
    "filtered": 205824,
    "unfiltered": 209120,
    "rssi": 185,
    "noise": 1,
    "glucose": 151
  }
]
