[
  {
    "_id": "577163e3ea06ef0a5f7246d8",
    "device": "dexcom",
    "date": 1467048714000,
    "dateString": "Mon Jun 27 13:31:54 EDT 2016",
    "sgv": 135,
    "direction": "Flat",
    "type": "sgv",
    "filtered": 165760,
    "unfiltered": 163616,
    "rssi": 677,
    "noise": 1,
    "glucose": 135
  },
  {
    "_id": "577162b8ea06ef0a5f7246d3",
    "device": "dexcom",
    "date": 1467048413000,
    "dateString": "Mon Jun 27 13:26:53 EDT 2016",
    "sgv": 136,
    "direction": "Flat",
    "type": "sgv",
    "filtered": 166592,
    "unfiltered": 164544,
    "rssi": 179,
    "noise": 1,
    "glucose": 136
  },
  {
    "_id": "5771618dea06ef0a5f7246cf",
    "device": "dexcom",
    "date": 1467048114000,
    "dateString": "Mon Jun 27 13:21:54 EDT 2016",
    "sgv": 137,
    "direction": "Flat",
    "type": "sgv",
    "filtered": 165760,
    "unfiltered": 165600,
    "rssi": 442,
    "noise": 1,
    "glucose": 137
  },
  {
    "_id": "57716060ea06ef0a5f7246cc",
    "device": "dexcom",
    "date": 1467047813000,
    "dateString": "Mon Jun 27 13:16:53 EDT 2016",
    "sgv": 137,
    "direction": "Flat",
    "type": "sgv",
    "filtered": 162816,
    "unfiltered": 166208,
    "rssi": 186,
    "noise": 1,
    "glucose": 137
  },
  {
    "_id": "57715f34ea06ef0a5f7246c8",
    "device": "dexcom",
    "date": 1467047513000,
    "dateString": "Mon Jun 27 13:11:53 EDT 2016",
    "sgv": 136,
    "direction": "Flat",
    "type": "sgv",
    "filtered": 158496,
    "unfiltered": 164768,
    "rssi": 181,
    "noise": 1,
    "glucose": 136
  },
  {
    "_id": "57715e09ea06ef0a5f7246c6",
    "device": "dexcom",
    "date": 1467047213000,
    "dateString": "Mon Jun 27 13:06:53 EDT 2016",
    "sgv": 133,
    "direction": "Flat",
    "type": "sgv",
    "filtered": 154368,
    "unfiltered": 162336,
    "rssi": 179,
    "noise": 1,
    "glucose": 133
  },
  {
    "_id": "57715cddea06ef0a5f7246c2",
    "device": "dexcom",
    "date": 1467046913000,
    "dateString": "Mon Jun 27 13:01:53 EDT 2016",
    "sgv": 128,
    "direction": "Flat",
    "type": "sgv",
    "filtered": 151680,
    "unfiltered": 157504,
    "rssi": 185,
    "noise": 1,
    "glucose": 128
  },
  {
    "_id": "57715bb1ea06ef0a5f7246ba",
    "device": "dexcom",
    "date": 1467046613000,
    "dateString": "Mon Jun 27 12:56:53 EDT 2016",
    "sgv": 123,
    "direction": "Flat",
    "type": "sgv",
    "filtered": 150592,
    "unfiltered": 152352,
    "rssi": 184,
    "noise": 1,
    "glucose": 123
  },
  {
    "_id": "57715a85ea06ef0a5f7246b7",
    "device": "dexcom",
    "date": 1467046313000,
    "dateString": "Mon Jun 27 12:51:53 EDT 2016",
    "sgv": 120,
    "direction": "Flat",
    "type": "sgv",
    "filtered": 150400,
    "unfiltered": 149984,
    "rssi": 180,
    "noise": 1,
    "glucose": 120
  },
  {
    "_id": "57715958ea06ef0a5f7246b3",
    "device": "dexcom",
    "date": 1467046013000,
    "dateString": "Mon Jun 27 12:46:53 EDT 2016",
    "sgv": 121,
    "direction": "Flat",
    "type": "sgv",
    "filtered": 150784,
    "unfiltered": 150720,
    "rssi": 185,
    "noise": 1,
    "glucose": 121
  }
]
