[
  {
    "_id": "577b7135ea06ef0a5f7267cc",
    "device": "dexcom",
    "date": 1467707638000,
    "dateString": "Tue Jul 05 04:33:58 EDT 2016",
    "sgv": 117,
    "direction": "FortyFiveUp",
    "type": "sgv",
    "filtered": 121776,
    "unfiltered": 132608,
    "rssi": 185,
    "noise": 1,
    "glucose": 117
  },
  {
    "_id": "577b7008ea06ef0a5f7267bf",
    "device": "dexcom",
    "date": 1467707338000,
    "dateString": "Tue Jul 05 04:28:58 EDT 2016",
    "sgv": 109,
    "direction": "Flat",
    "type": "sgv",
    "filtered": 118384,
    "unfiltered": 126704,
    "rssi": 184,
    "noise": 1,
    "glucose": 109
  },
  {
    "_id": "577b6eddea06ef0a5f7267bc",
    "device": "dexcom",
    "date": 1467707038000,
    "dateString": "Tue Jul 05 04:23:58 EDT 2016",
    "sgv": 97,
    "direction": "Flat",
    "type": "sgv",
    "filtered": 116848,
    "unfiltered": 117536,
    "rssi": 187,
    "noise": 1,
    "glucose": 97
  },
  {
    "_id": "577b6db4ea06ef0a5f7267b8",
    "device": "dexcom",
    "date": 1467706738000,
    "dateString": "Tue Jul 05 04:18:58 EDT 2016",
    "sgv": 96,
    "direction": "Flat",
    "type": "sgv",
    "filtered": 115808,
    "unfiltered": 116704,
    "rssi": 190,
    "noise": 1,
    "glucose": 96
  },
  {
    "_id": "577b6c88ea06ef0a5f7267b4",
    "device": "dexcom",
    "date": 1467706438000,
    "dateString": "Tue Jul 05 04:13:58 EDT 2016",
    "sgv": 96,
    "direction": "Flat",
    "type": "sgv",
    "filtered": 114528,
    "unfiltered": 116624,
    "rssi": 188,
    "noise": 1,
    "glucose": 96
  },
  {
    "_id": "577b6b5aea06ef0a5f7267b0",
    "device": "dexcom",
    "date": 1467706138000,
    "dateString": "Tue Jul 05 04:08:58 EDT 2016",
    "sgv": 95,
    "direction": "Flat",
    "type": "sgv",
    "filtered": 113792,
    "unfiltered": 115696,
    "rssi": 188,
    "noise": 1,
    "glucose": 95
  },
  {
    "_id": "577b6a2dea06ef0a5f7267ac",
    "device": "dexcom",
    "date": 1467705838000,
    "dateString": "Tue Jul 05 04:03:58 EDT 2016",
    "sgv": 93,
    "direction": "Flat",
    "type": "sgv",
    "filtered": 114736,
    "unfiltered": 114624,
    "rssi": 189,
    "noise": 1,
    "glucose": 93
  },
  {
    "_id": "577b6901ea06ef0a5f7267a7",
    "device": "dexcom",
    "date": 1467705538000,
    "dateString": "Tue Jul 05 03:58:58 EDT 2016",
    "sgv": 93,
    "direction": "FortyFiveDown",
    "type": "sgv",
    "filtered": 118128,
    "unfiltered": 114672,
    "rssi": 186,
    "noise": 1,
    "glucose": 93
  },
  {
    "_id": "577b67d5ea06ef0a5f7267a3",
    "device": "dexcom",
    "date": 1467705238000,
    "dateString": "Tue Jul 05 03:53:58 EDT 2016",
    "sgv": 95,
    "direction": "FortyFiveDown",
    "type": "sgv",
    "filtered": 123344,
    "unfiltered": 116208,
    "rssi": 187,
    "noise": 1,
    "glucose": 95
  },
  {
    "_id": "577b66a9ea06ef0a5f72679c",
    "device": "dexcom",
    "date": 1467704938000,
    "dateString": "Tue Jul 05 03:48:58 EDT 2016",
    "sgv": 98,
    "direction": "FortyFiveDown",
    "type": "sgv",
    "filtered": 128880,
    "unfiltered": 118432,
    "rssi": 187,
    "noise": 1,
    "glucose": 98
  }
]
