{
  "pump": {
    "battery": {
      "status": "normal", 
      "voltage": 1.39
    }, 
    "status": {
      "status": "normal", 
      "timestamp": "2016-07-09T15:16:41.000Z", 
      "bolusing": false, 
      "suspended": false
    }, 
    "reservoir": 68.8, 
    "clock": "2016-07-09T11:15:56-04:00"
  }, 
  "openaps": {
    "suggested": {
      "bg": 143, 
      "temp": "absolute", 
      "snoozeBG": 122, 
      "timestamp": "2016-07-09T15:16:48.000Z", 
      "rate": 1.75, 
      "reason": "Eventual BG 122>105, temp 1.5<1.75U/hr", 
      "eventualBG": 122, 
      "duration": 30, 
      "tick": "+3"
    }, 
    "iob": {
      "timestamp": "2016-07-09T15:16:45.000Z", 
      "activity": 0.003620555802469135, 
      "iob": 0.6668778242322709, 
      "bolusiob": 0
    }, 
    "enacted": {
      "bg": 143, 
      "temp": "absolute", 
      "snoozeBG": 122, 
      "recieved": true, 
      "reason": "Eventual BG 122>105, temp 1.5<1.75U/hr", 
      "rate": 1.75, 
      "eventualBG": 122, 
      "timestamp": "2016-07-09T15:16:52.000Z", 
      "duration": 30, 
      "tick": "+3"
    }
  }
}