{
  "pump": {
    "battery": {
      "status": "normal", 
      "voltage": 1.4
    }, 
    "status": {
      "status": "normal", 
      "timestamp": "2016-07-03T15:39:15.000Z", 
      "bolusing": false, 
      "suspended": false
    }, 
    "reservoir": 81.3, 
    "clock": "2016-07-03T11:38:25-04:00"
  }, 
  "openaps": {
    "suggested": {
      "bg": 128, 
      "temp": "absolute", 
      "snoozeBG": 102, 
      "timestamp": "2016-07-03T15:39:23.000Z", 
      "reason": "Eventual BG 96<105, temp 0.675 <~ req 0.73U/hr", 
      "eventualBG": 96, 
      "tick": "+0"
    }, 
    "iob": {
      "timestamp": "2016-07-03T15:39:19.000Z", 
      "activity": 0.020666260934744263, 
      "iob": 1.045747825793208, 
      "bolusiob": 0.10417151500000002
    }, 
    "enacted": {
      "bg": 130, 
      "temp": "absolute", 
      "snoozeBG": 107, 
      "recieved": true, 
      "reason": "Eventual BG 87<105, but Delta +2 > Exp. Delta -3.2; cancel", 
      "rate": 0, 
      "eventualBG": 87, 
      "timestamp": "2016-07-03T15:25:10.000Z", 
      "duration": 0, 
      "tick": "+2"
    }
  }
}