{
  "pump": {
    "battery": {
      "status": "normal", 
      "voltage": 1.55
    }, 
    "status": {
      "status": "normal", 
      "timestamp": "2016-06-16T00:30:26.000Z", 
      "bolusing": false, 
      "suspended": false
    }, 
    "reservoir": 102.1, 
    "clock": "2016-06-15T20:29:20-04:00"
  }, 
  "openaps": {
    "suggested": {
      "bg": 128, 
      "temp": "absolute", 
      "snoozeBG": 79, 
      "timestamp": "2016-06-16T00:30:33.000Z", 
      "rate": 0, 
      "reason": "Eventual BG 78<100, no temp, setting -0.1U/hr", 
      "eventualBG": 78, 
      "duration": 30, 
      "tick": -9
    }, 
    "iob": {
      "timestamp": "2016-06-16T00:30:29.000Z", 
      "activity": 0.017718280687830688, 
      "iob": 0.9173921460408221, 
      "bolusiob": 0.021371197760000026
    }, 
    "enacted": {
      "bg": 128, 
      "temp": "absolute", 
      "snoozeBG": 79, 
      "recieved": true, 
      "reason": "Eventual BG 78<100, no temp, setting -0.1U/hr", 
      "rate": 0, 
      "eventualBG": 78, 
      "timestamp": "2016-06-16T00:30:36.000Z", 
      "duration": 30, 
      "tick": -9
    }
  }
}