{
  "pump": {
    "battery": {
      "status": "normal", 
      "voltage": 1.56
    }, 
    "status": {
      "status": "normal", 
      "timestamp": "2016-07-06T10:09:45.000Z", 
      "bolusing": false, 
      "suspended": false
    }, 
    "reservoir": 68.5, 
    "clock": "2016-07-06T06:08:59-04:00"
  }, 
  "openaps": {
    "suggested": {
      "bg": 128, 
      "temp": "absolute", 
      "snoozeBG": 122, 
      "timestamp": "2016-07-06T10:09:52.000Z", 
      "reason": "Eventual BG 122>115, temp 1.55 >~ req 1.4U/hr", 
      "eventualBG": 122, 
      "tick": "+0"
    }, 
    "iob": {
      "timestamp": "2016-07-06T10:09:48.000Z", 
      "activity": 0.0019251951499118162, 
      "iob": 0.17413530362940058, 
      "bolusiob": 0
    }, 
    "enacted": {
      "bg": 127, 
      "temp": "absolute", 
      "snoozeBG": 122, 
      "recieved": true, 
      "reason": "Eventual BG 122>115, temp 1.05<1.25U/hr", 
      "rate": 1.25, 
      "eventualBG": 122, 
      "timestamp": "2016-07-06T09:47:29.000Z", 
      "duration": 30, 
      "tick": "+0"
    }
  }
}