{
  "pump": {
    "battery": {
      "status": "normal", 
      "voltage": 1.56
    }, 
    "status": {
      "status": "normal", 
      "timestamp": "2016-06-26T05:22:49.000Z", 
      "bolusing": false, 
      "suspended": false
    }, 
    "reservoir": 40.3, 
    "clock": "2016-06-26T01:21:55-04:00"
  }, 
  "openaps": {
    "suggested": {
      "bg": 152, 
      "temp": "absolute", 
      "snoozeBG": 131, 
      "timestamp": "2016-06-26T05:22:57.000Z", 
      "reason": "Eventual BG 131>115, temp 1.75 >~ req 1.65U/hr", 
      "eventualBG": 131, 
      "tick": "+0"
    }, 
    "iob": {
      "timestamp": "2016-06-26T05:22:53.000Z", 
      "activity": 0.00982067275132275, 
      "iob": 0.716913737948692, 
      "bolusiob": 0
    }, 
    "enacted": {
      "bg": 152, 
      "temp": "absolute", 
      "snoozeBG": 133, 
      "recieved": true, 
      "reason": "Eventual BG 133>115, no temp, setting 1.75U/hr", 
      "rate": 1.75, 
      "eventualBG": 133, 
      "timestamp": "2016-06-26T05:17:54.000Z", 
      "duration": 30, 
      "tick": "+8"
    }
  }
}