{
  "pump": {
    "battery": {
      "status": "normal", 
      "voltage": 1.33
    }, 
    "status": {
      "status": "normal", 
      "timestamp": "2016-05-30T06:59:17.000Z", 
      "bolusing": false, 
      "suspended": false
    }, 
    "reservoir": 89.2, 
    "clock": "2016-05-30T02:59:35-04:00"
  }, 
  "openaps": {
    "suggested": {
      "bg": 152, 
      "temp": "absolute", 
      "snoozeBG": 118, 
      "timestamp": "2016-05-30T06:59:27.000Z", 
      "rate": 0.75, 
      "reason": "Eventual BG 118<120, no temp, setting 0.75U/hr", 
      "eventualBG": 118, 
      "duration": 30, 
      "tick": -4
    }, 
    "iob": {
      "timestamp": "2016-05-30T06:59:22.000Z", 
      "activity": 0.00963015873015873, 
      "iob": 0.6675078222911112, 
      "bolusiob": 0
    }, 
    "enacted": {
      "bg": 152, 
      "temp": "absolute", 
      "snoozeBG": 118, 
      "recieved": true, 
      "reason": "Eventual BG 118<120, no temp, setting 0.75U/hr", 
      "rate": 0.75, 
      "eventualBG": 118, 
      "timestamp": "2016-05-30T06:59:33.000Z", 
      "duration": 30, 
      "tick": -4
    }
  }
}