{
  "pump": {
    "battery": {
      "status": "normal", 
      "voltage": 1.36
    }, 
    "status": {
      "status": "normal", 
      "timestamp": "2016-05-26T18:21:21.000Z", 
      "bolusing": false, 
      "suspended": false
    }, 
    "reservoir": 84.4, 
    "clock": "2016-05-26T14:21:39-04:00"
  }, 
  "openaps": {
    "suggested": {
      "bg": 133, 
      "temp": "absolute", 
      "snoozeBG": 92, 
      "timestamp": "2016-05-26T18:21:34.000Z", 
      "rate": 0.75, 
      "reason": "Eventual BG 69<95, no temp, setting 0.73U/hr", 
      "eventualBG": 69, 
      "duration": 30, 
      "tick": -2
    }, 
    "iob": {
      "timestamp": "2016-05-26T18:21:27.000Z", 
      "activity": 0.027555432098765428, 
      "iob": 1.955153060821111, 
      "bolusiob": 0.37595933866666653
    }, 
    "enacted": {
      "bg": 155, 
      "temp": "absolute", 
      "snoozeBG": 155, 
      "recieved": true, 
      "reason": "Eventual BG 155>100, adj. req. rate:3.7 to maxSafeBasal:1.7, no temp, setting 1.7U/hr", 
      "rate": 1.7, 
      "eventualBG": 155, 
      "timestamp": "2016-05-26T16:47:30.000Z", 
      "duration": 30, 
      "tick": "+1"
    }
  }
}