{
  "pump": {
    "battery": {
      "status": "normal", 
      "voltage": 1.46
    }, 
    "status": {
      "status": "normal", 
      "timestamp": "2016-06-27T10:17:17.000Z", 
      "bolusing": false, 
      "suspended": false
    }, 
    "reservoir": 98.9, 
    "clock": "2016-06-27T06:16:24-04:00"
  }, 
  "openaps": {
    "suggested": {
      "bg": 110, 
      "temp": "absolute", 
      "snoozeBG": 108, 
      "timestamp": "2016-06-27T10:17:24.000Z", 
      "reason": "Eventual BG 108<115, temp 0.675 <~ req 0.7U/hr", 
      "eventualBG": 108, 
      "tick": -2
    }, 
    "iob": {
      "timestamp": "2016-06-27T10:17:20.000Z", 
      "activity": 0.0016587905643738975, 
      "iob": -0.14003897890989409, 
      "bolusiob": 0
    }, 
    "enacted": {
      "bg": 114, 
      "temp": "absolute", 
      "snoozeBG": 108, 
      "recieved": true, 
      "reason": "Eventual BG 108<115, no temp, setting 0.7U/hr", 
      "rate": 0.675, 
      "eventualBG": 108, 
      "timestamp": "2016-06-27T10:08:50.000Z", 
      "duration": 30, 
      "tick": -5
    }
  }
}