{
  "pump": {
    "battery": {
      "status": "normal", 
      "voltage": 1.23
    }, 
    "status": {
      "status": "normal", 
      "timestamp": "2016-05-25T13:50:15.000Z", 
      "bolusing": false, 
      "suspended": false
    }, 
    "reservoir": 28.3, 
    "clock": "2016-05-25T09:50:31-04:00"
  }, 
  "openaps": {
    "suggested": {
      "bg": 102, 
      "temp": "absolute", 
      "snoozeBG": 95, 
      "timestamp": "2016-05-25T13:50:25.000Z", 
      "rate": 0, 
      "reason": "Eventual BG 95>95 but Avg. Delta -2.33 < Exp. Delta -0.6; cancel", 
      "eventualBG": 95, 
      "duration": 0, 
      "tick": -2
    }, 
    "iob": {
      "timestamp": "2016-05-25T13:50:19.000Z", 
      "activity": 0.003372980599647266, 
      "iob": 0.05198139316388892, 
      "bolusiob": 0
    }, 
    "enacted": {
      "bg": 102, 
      "temp": "absolute", 
      "snoozeBG": 95, 
      "recieved": true, 
      "reason": "Eventual BG 95>95 but Avg. Delta -2.33 < Exp. Delta -0.6; cancel", 
      "rate": 0, 
      "eventualBG": 95, 
      "timestamp": "2016-05-25T13:50:33.000Z", 
      "duration": 0, 
      "tick": -2
    }
  }
}