{
  "pump": {
    "battery": {
      "status": "normal", 
      "voltage": 1.57
    }, 
    "status": {
      "status": "normal", 
      "timestamp": "2016-06-17T08:36:47.000Z", 
      "bolusing": false, 
      "suspended": false
    }, 
    "reservoir": 58.9, 
    "clock": "2016-06-17T04:35:45-04:00"
  }, 
  "openaps": {
    "suggested": {
      "bg": 116, 
      "temp": "absolute", 
      "snoozeBG": 121, 
      "timestamp": "2016-06-17T08:36:54.000Z", 
      "reason": "Eventual BG 121>115, temp 1.1 >~ req 1.15U/hr", 
      "eventualBG": 121, 
      "tick": "+1"
    }, 
    "iob": {
      "timestamp": "2016-06-17T08:36:51.000Z", 
      "activity": 0.0005252116402116401, 
      "iob": -0.06758986817854168, 
      "bolusiob": 0
    }, 
    "enacted": {
      "bg": 115, 
      "temp": "absolute", 
      "snoozeBG": 120, 
      "recieved": true, 
      "reason": "Eventual BG 120>115, no temp, setting 1.1U/hr", 
      "rate": 1.1, 
      "eventualBG": 120, 
      "timestamp": "2016-06-17T08:32:02.000Z", 
      "duration": 30, 
      "tick": "+1"
    }
  }
}